Workbook

Sheet CÁLC-EVM-30%
A1: Cálculos EVM al 30% de avance
A2: Métrica | B2: Valor / Fórmula | C2: Interpretación | D2: Consecuencia en el proyecto | E2: Comentarios
A3: BAC | B3: 79000 | C3: Presupuesto total reportado para el cálculo EVM al 30%. | D3: Sirve como base para EAC y TCPI. | E3: Parte 5: BAC reportado USD 79,000.
A4: PV | B4: 25000 | C4: Valor planificado a la fecha de corte. | D4: Mide cuánto se esperaba haber avanzado en valor presupuestado. | E4: Parte 5: PV USD 25,000.
A5: EV | B5: 21000 | C5: Valor ganado realmente por el avance ejecutado. | D5: Base para medir variaciones de costo y cronograma. | E5: Parte 5: EV USD 21,000.
A6: AC | B6: 26500 | C6: Costo real incurrido al corte. | D6: Permite evidenciar si el proyecto está gastando más que el valor generado. | E6: Parte 5: AC USD 26,500.
A7: CV | B7: =B5-B6 -> -5500 | C7: Desviación de costo negativa: se gastó más de lo que se ganó. | D7: El proyecto presenta sobrecosto; se está consumiendo margen. | E7: Calculado.
A8: SV | B8: =B5-B4 -> -4000 | C8: Desviación de cronograma negativa: se avanzó menos de lo planificado. | D8: El proyecto presenta retraso respecto al plan. | E8: Calculado.
A9: CPI | B9: =B5/B6 -> 0.79245283 | C9: Por cada USD 1 gastado, se genera aprox. USD 0.79 de valor. | D9: Ineficiencia de costos y riesgo de exceder presupuesto. | E9: Calculado.
A10: SPI | B10: =B5/B4 -> 0.84 | C10: Por cada 1 unidad de avance planificado, solo se logró 0.84. | D10: Retraso y riesgo de incumplimiento de hitos. | E10: Calculado.
A11: EAC desempeño actual | B11: =B3/B9 -> 99690.476 | C11: Costo final estimado si el desempeño actual continúa. | D11: El costo proyectado supera el BAC y reduce margen. | E11: Calculado con BAC 79,000 reportado en parte 5.
A12: EAC recuperando desempeño planificado | B12: =B6+(B3-B5) -> 84500 | C12: Costo final si desde el corte se recupera el desempeño planificado. | D12: Escenario más controlado, pero requiere gestión correctiva. | E12: Calculado.
A13: TCPI para cumplir BAC | B13: =(B3-B5)/(B3-B6) -> 1.1047619 | C13: Eficiencia requerida para completar dentro del BAC original. | D13: Mayor a 1: difícil de lograr sin acciones fuertes de control. | E13: Calculado.
A16: Conclusión ejecutiva EVM
A17: El proyecto se encuentra en una condición desfavorable al 30% del avance: CV y SV son negativos, CPI es menor a 1 y SPI es menor a 1. Esto evidencia sobrecosto y retraso. El TCPI mayor a 1 indica que cumplir el presupuesto original exige una eficiencia superior al desempeño actual, por lo que se recomienda replanificar, controlar costos y formalizar los impactos mediante Change Requests.

Sheet ESCENARIOS FINANCIEROS
A1: Escenarios financieros y de respuesta
A2: Escenario | B2: Descripción | C2: Costo base | D2: Impacto compliance | E2: Penalidad | F2: Ingreso | G2: Costo total | H2: Resultado P&L | I2: Margen % | J2: Conclusión
A3: 1. No hacer nada | B3: Se mantiene el desempeño actual y se absorbe el impacto explícito de compliance y la penalidad por 5 días. | C3: ='CÁLC-EVM-30%'!B11 -> 99690.476 | D3: =6000 -> 6000 | E3: =800*5 -> 4000 | F3: =105000 -> 105000 | G3: =C3+D3+E3 -> 109690.48 | H3: =F3-G3 -> -4690.4762 | I3: =((F3-G3)/F3) -> -0.044671202 | J3: Escenario crítico: el proyecto entra en pérdida, consume el margen y expone al equipo a incumplimiento.
A4: 2. Propuesta principal | B4: Formalizar CR por compliance: el cliente reconoce los USD 6,000. Se replanifica el plazo de 5 días vía aprobación formal. | C4: ='CÁLC-EVM-30%'!B12 -> 84500 | D4: =6000 -> 6000 | E4: =0 -> 0 | F4: =105000+D4 -> 111000 | G4: =C4+D4+E4 -> 90500 | H4: =F4-G4 -> 20500 | I4: =((F4-G4)/F4) -> 0.18468468 | J4: Escenario recomendado: protege margen, da trazabilidad contractual y reduce riesgo de penalidad.
A5: 3. Alternativa rechazada | B5: Absorber compliance sin CR, aunque se recupere parcialmente el desempeño planificado. | C5: ='CÁLC-EVM-30%'!B12 -> 84500 | D5: =6000 -> 6000 | E5: =800*5 -> 4000 | F5: =105000 -> 105000 | G5: =C5+D5+E5 -> 94500 | H5: =F5-G5 -> 10500 | I5: =((F5-G5)/F5) -> 0.1 | J5: No recomendado: aunque mejora el costo base, la empresa asume costos y penalidad, reduciendo rentabilidad.
A8: Explicación de los escenarios
A9: Escenario 1: Se usa el EAC de desempeño actual porque representa la continuidad de la tendencia negativa del proyecto. Se suma el costo explícito de compliance (USD 6,000) y la penalidad explícita de 5 días x USD 800/día.
A10: Escenario 2: Es la propuesta principal porque convierte el impacto de compliance en un Change Request. El ingreso aumenta por reconocimiento del cambio y no se aplica penalidad, ya que el cambio de alcance debe formalizar su impacto en plazo.
A11: Escenario 3: Se muestra como alternativa rechazada: recuperar desempeño ayuda, pero absorber compliance y penalidad sin CR destruye parte del margen y deja al proveedor expuesto.

Sheet 3_P&L
A1: P&L proyectado del proyecto
A2: Concepto | B2: Base inicial | C2: Escenario 1: No hacer nada | D2: Escenario 2: Propuesta principal | E2: Escenario 3: Alternativa rechazada | F2: Fórmula / lógica | G2: Conclusión
A3: Ingreso contractual | B3: 105000 | C3: ='ESCENARIOS FINANCIEROS'!F3 -> 105000 | D3: ='ESCENARIOS FINANCIEROS'!F4 -> 111000 | E3: ='ESCENARIOS FINANCIEROS'!F5 -> 105000 | F3: Precio de venta contractual. En la propuesta principal aumenta por CR de compliance. | G3: Base para medir rentabilidad.
A4: Costo estimado inicial | B4: 80000 | C4: 80000 | D4: 80000 | E4: 80000 | F4: Costo estimado contractual del proyecto. | G4: Base inicial del proyecto.
A5: Costo proyectado/EAC | B5: ='CÁLC-EVM-30%'!B3 -> 79000 | C5: ='ESCENARIOS FINANCIEROS'!C3 -> 99690.476 | D5: ='ESCENARIOS FINANCIEROS'!C4 -> 84500 | E5: ='ESCENARIOS FINANCIEROS'!C5 -> 84500 | F5: EAC según desempeño actual o recuperación planificada; para base inicial se usa costo proyectado de 79 000 USD | G5: Determina el costo probable de cierre.
A6: Impacto compliance | B6: 0 | C6: ='ESCENARIOS FINANCIEROS'!D3 -> 6000 | D6: ='ESCENARIOS FINANCIEROS'!D4 -> 6000 | E6: ='ESCENARIOS FINANCIEROS'!D5 -> 6000 | F6: Dato explícito del evento 2: USD 6,000. | G6: Aumenta costo si no se gestiona como CR.
A7: Penalidad | B7: 0 | C7: ='ESCENARIOS FINANCIEROS'!E3 -> 4000 | D7: ='ESCENARIOS FINANCIEROS'!E4 -> 0 | E7: ='ESCENARIOS FINANCIEROS'!E5 -> 4000 | F7: Dato explícito: 5 días x USD 800/día. | G7: Reduce utilidad si aplica retraso.
A8: Costo total | B8: =B7+B5+B6 -> 79000 | C8: ='ESCENARIOS FINANCIEROS'!G3 -> 109690.48 | D8: ='ESCENARIOS FINANCIEROS'!G4 -> 90500 | E8: ='ESCENARIOS FINANCIEROS'!G5 -> 94500 | F8: Costo proyectado + compliance + penalidad. | G8: Permite comparar contra ingreso.
A9: Resultado P&L | B9: =B3-B8 -> 26000 | C9: ='ESCENARIOS FINANCIEROS'!H3 -> -4690.4762 | D9: ='ESCENARIOS FINANCIEROS'!H4 -> 20500 | E9: ='ESCENARIOS FINANCIEROS'!H5 -> 10500 | F9: Ingreso - costo total. | G9: Indica ganancia o pérdida.
A10: Margen % | B10: =B9/B3 -> 0.24761905 | C10: =C9/C3 -> -0.044671202 | D10: =D9/D3 -> 0.18468468 | E10: =E9/E3 -> 0.1 | F10: Resultado P&L / ingreso. | G10: Mide rentabilidad final.
A11: Conclusión P&L
A12: El P&L calcula el margen con la fórmula correcta: Resultado P&L / Ingreso. La base inicial muestra utilidad de USD 26,000 y margen de 24.76%. El escenario 1 destruye el margen porque combina EAC alto, compliance y penalidad. La propuesta principal es la más sólida porque formaliza el cambio y protege la rentabilidad.
